{"name":"autorization","id":"tests.mainTests:autorization","testCaseName":"tests.mainTests","userStory":{"id":"tests.mainTests","storyName":"Main tests","storyClassName":"tests.mainTests","path":"tests","type":"story"},"featureTag":{"name":"Main tests","type":"story"},"title":"Autorization","tags":[{"name":"Main tests","type":"story"}],"startTime":"2018-10-09T15:31:08.663+03:00[Europe/Moscow]","duration":22763,"testFailureCause":{"errorType":"java.net.ConnectException","message":"Connection timed out: connect","stackTrace":[{"declaringClass":"org.apache.http.conn.scheme.PlainSocketFactory","methodName":"connectSocket","fileName":"PlainSocketFactory.java","lineNumber":121},{"declaringClass":"org.apache.http.impl.conn.DefaultClientConnectionOperator","methodName":"openConnection","fileName":"DefaultClientConnectionOperator.java","lineNumber":180},{"declaringClass":"org.apache.http.impl.conn.ManagedClientConnectionImpl","methodName":"open","fileName":"ManagedClientConnectionImpl.java","lineNumber":326},{"declaringClass":"org.apache.http.impl.client.DefaultRequestDirector","methodName":"tryConnect","fileName":"DefaultRequestDirector.java","lineNumber":610},{"declaringClass":"org.apache.http.impl.client.DefaultRequestDirector","methodName":"execute","fileName":"DefaultRequestDirector.java","lineNumber":445},{"declaringClass":"org.apache.http.impl.client.AbstractHttpClient","methodName":"doExecute","fileName":"AbstractHttpClient.java","lineNumber":835},{"declaringClass":"org.apache.http.impl.client.CloseableHttpClient","methodName":"execute","fileName":"CloseableHttpClient.java","lineNumber":83},{"declaringClass":"org.apache.http.impl.client.CloseableHttpClient","methodName":"execute","fileName":"CloseableHttpClient.java","lineNumber":56},{"declaringClass":"io.restassured.internal.http.HTTPBuilder","methodName":"post","fileName":"HTTPBuilder.java","lineNumber":349},{"declaringClass":"io.restassured.internal.RequestSpecificationImpl","methodName":"sendRequest","fileName":"RequestSpecificationImpl.groovy","lineNumber":1269},{"declaringClass":"groovy.lang.MetaMethod","methodName":"doMethodInvoke","fileName":"MetaMethod.java","lineNumber":325},{"declaringClass":"groovy.lang.MetaClassImpl","methodName":"invokeMethod","fileName":"MetaClassImpl.java","lineNumber":1213},{"declaringClass":"groovy.lang.MetaClassImpl","methodName":"invokeMethod","fileName":"MetaClassImpl.java","lineNumber":1022},{"declaringClass":"groovy.lang.MetaClassImpl","methodName":"invokeMethod","fileName":"MetaClassImpl.java","lineNumber":810},{"declaringClass":"io.restassured.internal.RequestSpecificationImpl","methodName":"invokeMethod","fileName":"RequestSpecificationImpl.groovy","lineNumber":-1},{"declaringClass":"io.restassured.internal.filter.SendRequestFilter","methodName":"filter","fileName":"SendRequestFilter.groovy","lineNumber":30},{"declaringClass":"io.restassured.internal.filter.FilterContextImpl","methodName":"next","fileName":"FilterContextImpl.groovy","lineNumber":72},{"declaringClass":"io.restassured.filter.time.TimingFilter","methodName":"filter","fileName":"TimingFilter.java","lineNumber":56},{"declaringClass":"io.restassured.internal.filter.FilterContextImpl","methodName":"next","fileName":"FilterContextImpl.groovy","lineNumber":72},{"declaringClass":"io.restassured.internal.RequestSpecificationImpl","methodName":"applyPathParamsAndSendRequest","fileName":"RequestSpecificationImpl.groovy","lineNumber":1722},{"declaringClass":"groovy.lang.MetaMethod","methodName":"doMethodInvoke","fileName":"MetaMethod.java","lineNumber":325},{"declaringClass":"groovy.lang.MetaClassImpl","methodName":"invokeMethod","fileName":"MetaClassImpl.java","lineNumber":1213},{"declaringClass":"groovy.lang.MetaClassImpl","methodName":"invokeMethod","fileName":"MetaClassImpl.java","lineNumber":1022},{"declaringClass":"groovy.lang.MetaClassImpl","methodName":"invokeMethod","fileName":"MetaClassImpl.java","lineNumber":810},{"declaringClass":"io.restassured.internal.RequestSpecificationImpl","methodName":"invokeMethod","fileName":"RequestSpecificationImpl.groovy","lineNumber":-1},{"declaringClass":"io.restassured.internal.RequestSpecificationImpl","methodName":"applyPathParamsAndSendRequest","fileName":"RequestSpecificationImpl.groovy","lineNumber":1728},{"declaringClass":"groovy.lang.MetaMethod","methodName":"doMethodInvoke","fileName":"MetaMethod.java","lineNumber":325},{"declaringClass":"groovy.lang.MetaClassImpl","methodName":"invokeMethod","fileName":"MetaClassImpl.java","lineNumber":1213},{"declaringClass":"groovy.lang.MetaClassImpl","methodName":"invokeMethod","fileName":"MetaClassImpl.java","lineNumber":1022},{"declaringClass":"groovy.lang.MetaClassImpl","methodName":"invokeMethod","fileName":"MetaClassImpl.java","lineNumber":810},{"declaringClass":"io.restassured.internal.RequestSpecificationImpl","methodName":"invokeMethod","fileName":"RequestSpecificationImpl.groovy","lineNumber":-1},{"declaringClass":"io.restassured.internal.RequestSpecificationImpl","methodName":"post","fileName":"RequestSpecificationImpl.groovy","lineNumber":172},{"declaringClass":"io.restassured.internal.RequestSpecificationImpl","methodName":"post","fileName":"RequestSpecificationImpl.groovy","lineNumber":-1},{"declaringClass":"tests.mainTests","methodName":"autorization","fileName":"mainTests.kt","lineNumber":17}]},"testFailureClassname":"java.net.ConnectException","testFailureMessage":"Connection timed out: connect","testFailureSummary":"ERROR;java.net.ConnectException;Connection timed out: connect;PlainSocketFactory.java","projectKey":"","annotatedResult":"ERROR","manual":false,"testSource":"JUnit","result":"ERROR"}